phobos/__init__.py
phobos/cli/__init__.py
phobos/cli/connections/__init__.py
phobos/cli/connections/arche.py
phobos/cli/connections/europa.py
phobos/cli/cookiecutter-phobos-project/README.md
phobos/cli/cookiecutter-phobos-project/cookiecutter.json
phobos/cli/cookiecutter-phobos-project/{{cookiecutter.project_name}}/.gitignore
phobos/cli/cookiecutter-phobos-project/{{cookiecutter.project_name}}/.polyaxonignore
phobos/cli/cookiecutter-phobos-project/{{cookiecutter.project_name}}/checkpoints/checkpoint_epoch_1.pt
phobos/cli/cookiecutter-phobos-project/{{cookiecutter.project_name}}/metadata.yaml
phobos/cli/cookiecutter-phobos-project/{{cookiecutter.project_name}}/requirements.txt
phobos/cli/cookiecutter-phobos-project/{{cookiecutter.project_name}}/run.sh
phobos/cli/cookiecutter-phobos-project/{{cookiecutter.project_name}}/train.py
phobos/cli/dataset.py
phobos/cli/experiment.py
phobos/cli/loss.py
phobos/cli/metric.py
phobos/cli/model.py
phobos/cli/project.py
phobos/cli/utils/__init__.py
phobos/cli/utils/execution.py
phobos/cli/utils/polyaxonfile.py
phobos/dataset/__init__.py
phobos/dataset/dataset.py
phobos/dataset/input.py
phobos/dataset/loader.py
phobos/dataset/output.py
phobos/dataset/streams.py
phobos/dataset/streams.py.bak
phobos/grain/__init__.py
phobos/grain/grain.py
phobos/loss/__init__.py
phobos/loss/_functional.py
phobos/loss/bce_jaccard.py
phobos/loss/constants.py
phobos/loss/dice.py
phobos/loss/dice_spline.py
phobos/loss/focal.py
phobos/loss/jaccard.py
phobos/loss/lovasz.py
phobos/loss/soft_bce.py
phobos/loss/soft_ce.py
phobos/loss/spline.py
phobos/loss/tversky.py
phobos/loss/utils.py
phobos/metrics/__init__.py
phobos/metrics/utils.py
phobos/models/__init__.py
phobos/models/classification/__init__.py
phobos/models/classification/alexnet.py
phobos/models/classification/resnet.py
phobos/models/segmentation/__init__.py
phobos/models/segmentation/base/__init__.py
phobos/models/segmentation/base/heads.py
phobos/models/segmentation/base/initialization.py
phobos-1.2.9.dist-info/entry_points.txt
phobos-1.2.9.dist-info/LICENSE
phobos-1.2.9.dist-info/WHEEL
phobos-1.2.9.dist-info/METADATA
phobos-1.2.9.dist-info/RECORD
