Metadata-Version: 2.1
Name: phobos
Version: 1.2.9
Summary: Training utility library and config manager for Granular Machine Vision research
Home-page: https://github.com/granularai/phobos
License: MIT
Author: Sagar Verma
Author-email: sagar@granular.ai
Requires-Python: >=3.7.0,<4.0.0
Classifier: Intended Audience :: Developers
Classifier: License :: OSI Approved :: MIT License
Classifier: Natural Language :: English
Classifier: Programming Language :: Python :: 3
Classifier: Programming Language :: Python :: 3.10
Classifier: Programming Language :: Python :: 3.7
Classifier: Programming Language :: Python :: 3.8
Classifier: Programming Language :: Python :: 3.9
Requires-Dist: Shapely (>=1.8.1,<2.0.0)
Requires-Dist: albumentations (>=1.0.3,<2.0.0)
Requires-Dist: appdirs (>=1.4.4,<2.0.0)
Requires-Dist: boto3 (>=1.21.36,<2.0.0)
Requires-Dist: cookiecutter (>=1.7.3,<2.0.0)
Requires-Dist: efficientnet-pytorch (>=0.7.1,<0.8.0)
Requires-Dist: numpy (>=1.21.0,<2.0.0)
Requires-Dist: polyaxon (>=1.10.1,<2.0.0)
Requires-Dist: polyaxon-sdk (>=1.10.1,<2.0.0)
Requires-Dist: pretrainedmodels (>=0.7.4,<0.8.0)
Requires-Dist: pytorch-lightning (>=1.3.8,<2.0.0)
Requires-Dist: rasterio (>=1.2.10,<2.0.0)
Requires-Dist: scikit-learn (>=0.24.2,<0.25.0)
Requires-Dist: timm (==0.5.4)
Requires-Dist: torch (>=1.10.1,<2.0.0)
Requires-Dist: torchvision (>=0.11.2,<0.12.0)
Requires-Dist: webdataset (==0.1.62)
Requires-Dist: yacs (>=0.1.8,<0.2.0)
Project-URL: Repository, https://github.com/granularai/phobos
